setup.py
tomshapes/Circle.py
tomshapes/Shape.py
tomshapes/__init__.py
tomshapes/test.py
tomshapes.egg-info/PKG-INFO
tomshapes.egg-info/SOURCES.txt
tomshapes.egg-info/dependency_links.txt
tomshapes.egg-info/top_level.txt