Metadata-Version: 1.0
Name: tomshapes
Version: 1.0.1
Summary: Python Shapes distro
Home-page: https://nothing.com/
Author: Tom Mathew
Author-email: something@nothing.com
License: UNKNOWN
Platform: UNKNOWN
